wordsearchgen/__init__.py
wordsearchgen/__main__.py
wordsearchgen/algorithm.py
wordsearchgen/gui_common.py
wordsearchgen/qt_mainwindow.py
wordsearchgen/tk_mainwindow.py
word_search_app-3.2.4.dist-info/METADATA
word_search_app-3.2.4.dist-info/WHEEL
word_search_app-3.2.4.dist-info/entry_points.txt
word_search_app-3.2.4.dist-info/licenses/LICENSE
word_search_app-3.2.4.dist-info/RECORD
