Metadata-Version: 2.4
Name: word-search-app
Version: 3.2.4
Summary: Generate word search puzzles
Project-URL: Homepage, https://github.com/thelabcat/word-search-generator
Project-URL: Issues, https://github.com/thelabcat/word-search-generator/issues
Author-email: Wilbur Jaywright <zargulthewizard@outlook.com>
License-File: LICENSE
Keywords: WordSearch,app,games,generator,puzzles
Classifier: Development Status :: 4 - Beta
Classifier: License :: OSI Approved :: GNU General Public License v3 or later (GPLv3+)
Classifier: Operating System :: OS Independent
Classifier: Programming Language :: Python :: 3
Requires-Python: >=3.11.2
Requires-Dist: numpy
Requires-Dist: pyside6
